{
  "code": 200,
  "data": {
    "courselist": [
      {
        "id": "9",
        "name": "初识HTML+CSS",
        "short_description": "HTML+CSS基础教程8小时带领大家步步深入学习标签用法和意义",
        "pic": "//img2.mukewang.com/529dc3380001379906000338-590-330.jpg",
        "numbers": "1091760",
        "type": 1,
        "share": "https://www.imooc.com/learn/9",
        "is_learned": 0,
        "learn_rate": -1,
        "is_pay": "0",
        "level": "入门",
        "skill_id": "7",
        "skill_name": "HTML/CSS",
        "skill_pic": "//img3.mukewang.com/5b1744f9000101ce02400240.jpg",
        "skill_color": "43b7ff"
      },
      {
        "id": "85",
        "name": "Java入门第一季",
        "short_description": "本教程从Java环境搭建、工具使用、基础语法开始，带你入门",
        "pic": "//img.mukewang.com/57035ff200014b8a06000338-590-330.jpg",
        "numbers": "1037098",
        "type": 1,
        "share": "https://www.imooc.com/learn/85",
        "is_learned": 0,
        "learn_rate": -1,
        "is_pay": "0",
        "level": "入门",
        "skill_id": "220",
        "skill_name": "Java",
        "skill_pic": "//img1.mukewang.com/5b1746ca000157da02400240.jpg",
        "skill_color": "ff4545"
      },
      {
        "id": "249",
        "name": "C语言入门",
        "short_description": "C语言入门视频教程，带你进入编程世界的必修课-C语言",
        "pic": "//img4.mukewang.com/574669dc0001993606000338-590-330.jpg",
        "numbers": "795754",
        "type": 1,
        "share": "https://www.imooc.com/learn/249",
        "is_learned": 0,
        "learn_rate": -1,
        "is_pay": "0",
        "level": "入门",
        "skill_id": "1273",
        "skill_name": "C",
        "skill_pic": "//img4.mukewang.com/5b1746f7000114fd02400240.jpg",
        "skill_color": "27c6ff"
      },
      {
        "id": "177",
        "name": "初识Python",
        "short_description": "学python入门视频教程，让你快速入门并能编写简单的Python程序",
        "pic": "//img3.mukewang.com/540e57300001d6d906000338-590-330.jpg",
        "numbers": "713168",
        "type": 1,
        "share": "https://www.imooc.com/learn/177",
        "is_learned": 0,
        "learn_rate": -1,
        "is_pay": "0",
        "level": "入门",
        "skill_id": "1118",
        "skill_name": "Python",
        "skill_pic": "//img2.mukewang.com/5b1746ed0001976102400240.jpg",
        "skill_color": "0070bb"
      },
      {
        "id": "36",
        "name": "JavaScript入门篇",
        "short_description": "JavaScript做为一名Web工程师的必备技术，本教程让您快速入门",
        "pic": "//img4.mukewang.com/53e1d0470001ad1e06000338-590-330.jpg",
        "numbers": "676766",
        "type": 1,
        "share": "https://www.imooc.com/learn/36",
        "is_learned": 0,
        "learn_rate": -1,
        "is_pay": "0",
        "level": "入门",
        "skill_id": "44",
        "skill_name": "JavaScript",
        "skill_pic": "//img3.mukewang.com/5b1893f90001d25702400240.jpg",
        "skill_color": "eb3030"
      },
      {
        "id": "139",
        "name": "PS入门教程——新手过招",
        "short_description": "慕课网推出的PS入门教程，PS入门学习必备课程，带你轻松入门",
        "pic": "//img2.mukewang.com/53a28e960001311b06000338-590-330.jpg",
        "numbers": "592862",
        "type": 1,
        "share": "https://www.imooc.com/learn/139",
        "is_learned": 0,
        "learn_rate": -1,
        "is_pay": "0",
        "level": "入门",
        "skill_id": "4733",
        "skill_name": "设计工具",
        "skill_pic": "//img.mukewang.com/5b174b64000128c702400240.jpg",
        "skill_color": "4a95dc"
      },
      {
        "id": "124",
        "name": "Java入门第二季",
        "short_description": "Java 面向对象编程基本实现原理，进一步探索 Java 世界的奥秘",
        "pic": "//img4.mukewang.com/570360620001390f06000338-590-330.jpg",
        "numbers": "488962",
        "type": 1,
        "share": "https://www.imooc.com/learn/124",
        "is_learned": 0,
        "learn_rate": -1,
        "is_pay": "0",
        "level": "入门",
        "skill_id": "220",
        "skill_name": "Java",
        "skill_pic": "//img.mukewang.com/5b1746ca000157da02400240.jpg",
        "skill_color": "ff4545"
      },
      {
        "id": "54",
        "name": "PHP入门篇",
        "short_description": "PHP入门教程轻松学习，行业大牛帮您快速掌握PHP编程基础知识。",
        "pic": "//img1.mukewang.com/53daee770001dd0706000338-590-330.jpg",
        "numbers": "434471",
        "type": 1,
        "share": "https://www.imooc.com/learn/54",
        "is_learned": 0,
        "learn_rate": -1,
        "is_pay": "0",
        "level": "入门",
        "skill_id": "1",
        "skill_name": "PHP",
        "skill_pic": "//img2.mukewang.com/5b174699000182b802400240.jpg",
        "skill_color": "5280f1"
      },
      {
        "id": "10",
        "name": "JavaScript进阶篇",
        "short_description": "本课程从如何插入JS代码开始，带您进入网页动态交互世界",
        "pic": "//img1.mukewang.com/574678bd00010a7206000338-590-330.jpg",
        "numbers": "429995",
        "type": 1,
        "share": "https://www.imooc.com/learn/10",
        "is_learned": 0,
        "learn_rate": -1,
        "is_pay": "0",
        "level": "入门",
        "skill_id": "44",
        "skill_name": "JavaScript",
        "skill_pic": "//img1.mukewang.com/5b1893f90001d25702400240.jpg",
        "skill_color": "eb3030"
      },
      {
        "id": "122",
        "name": "与MySQL的零距离接触",
        "short_description": "本课程涵盖全部MySQL数据库的基础，学习MySQL数据库的基础知识",
        "pic": "//img.mukewang.com/570756b0000146fc06000338-590-330.jpg",
        "numbers": "387532",
        "type": 1,
        "share": "https://www.imooc.com/learn/122",
        "is_learned": 0,
        "learn_rate": -1,
        "is_pay": "0",
        "level": "入门",
        "skill_id": "952",
        "skill_name": "MySQL",
        "skill_pic": "//img4.mukewang.com/5b1749940001ab5a02400240.jpg",
        "skill_color": "5892ee"
      },
      {
        "id": "110",
        "name": "Java入门第三季",
        "short_description": "Java中你必须懂得常用技能，不容错过的精彩，快来加入吧",
        "pic": "//img2.mukewang.com/5703604a0001694406000338-590-330.jpg",
        "numbers": "382918",
        "type": 1,
        "share": "https://www.imooc.com/learn/110",
        "is_learned": 0,
        "learn_rate": -1,
        "is_pay": "0",
        "level": "入门",
        "skill_id": "220",
        "skill_name": "Java",
        "skill_pic": "//img1.mukewang.com/5b1746ca000157da02400240.jpg",
        "skill_color": "ff4545"
      },
      {
        "id": "175",
        "name": " Linux达人养成计划 I",
        "short_description": "Linux入门视频教程，以通俗易懂的语言带你感受linux之美",
        "pic": "//img1.mukewang.com/57035f110001a57906000338-590-330.jpg",
        "numbers": "369436",
        "type": 1,
        "share": "https://www.imooc.com/learn/175",
        "is_learned": 0,
        "learn_rate": -1,
        "is_pay": "0",
        "level": "入门",
        "skill_id": "468",
        "skill_name": "Linux",
        "skill_pic": "//img2.mukewang.com/5b174ae20001c83502400240.jpg",
        "skill_color": "5b78d5"
      },
      {
        "id": "159",
        "name": "PS大神通关教程",
        "short_description": "讲师分享实战经验，让你真正掌握PS使用方，实现ps菜鸟到大神的逆袭",
        "pic": "//img3.mukewang.com/53d068840001a89906000338-590-330.jpg",
        "numbers": "367360",
        "type": 1,
        "share": "https://www.imooc.com/learn/159",
        "is_learned": 0,
        "learn_rate": -1,
        "is_pay": "0",
        "level": "入门",
        "skill_id": "4733",
        "skill_name": "设计工具",
        "skill_pic": "//img1.mukewang.com/5b174b64000128c702400240.jpg",
        "skill_color": "4a95dc"
      },
      {
        "id": "141",
        "name": "玩转Bootstrap（基础）",
        "short_description": "告诉你使用Bootstrap，并且能够独立定制出适合自己的Bootstrap",
        "pic": "//img4.mukewang.com/5704ae850001f59906000338-590-330.jpg",
        "numbers": "302155",
        "type": 1,
        "share": "https://www.imooc.com/learn/141",
        "is_learned": 0,
        "learn_rate": -1,
        "is_pay": "0",
        "level": "初级",
        "skill_id": "1263",
        "skill_name": "Bootstrap",
        "skill_pic": "//img.mukewang.com/5b17461400017dee02400240.jpg",
        "skill_color": "00c7c7"
      },
      {
        "id": "342",
        "name": "C++远征之起航篇",
        "short_description": "C++亮点尽在其中，本课程是在C语言基础上的一个延伸，得以升华",
        "pic": "//img3.mukewang.com/5707604300018d0406000338-590-330.jpg",
        "numbers": "275973",
        "type": 1,
        "share": "https://www.imooc.com/learn/342",
        "is_learned": 0,
        "learn_rate": -1,
        "is_pay": "0",
        "level": "入门",
        "skill_id": "1331",
        "skill_name": "C++",
        "skill_pic": "//img3.mukewang.com/5b1747010001b67902400240.jpg",
        "skill_color": "45ec60"
      },
      {
        "id": "277",
        "name": "JavaScript深入浅出",
        "short_description": "由浅入深学习JS语言特性，且解析JS常见误区，从入门到掌握",
        "pic": "//img.mukewang.com/5705d3a3000129d006000338-590-330.jpg",
        "numbers": "265824",
        "type": 1,
        "share": "https://www.imooc.com/learn/277",
        "is_learned": 0,
        "learn_rate": -1,
        "is_pay": "0",
        "level": "中级",
        "skill_id": "44",
        "skill_name": "JavaScript",
        "skill_pic": "//img.mukewang.com/5b1893f90001d25702400240.jpg",
        "skill_color": "eb3030"
      },
      {
        "id": "506",
        "name": "前端工程师必备的PS技能——切图篇",
        "short_description": "前端开发需要的Photoshop技巧，结合实际例子教会大家如何操作",
        "pic": "//img4.mukewang.com/578741d3000151e806000338-590-330.jpg",
        "numbers": "255283",
        "type": 1,
        "share": "https://www.imooc.com/learn/506",
        "is_learned": 0,
        "learn_rate": -1,
        "is_pay": "0",
        "level": "初级",
        "skill_id": "4733",
        "skill_name": "设计工具",
        "skill_pic": "//img3.mukewang.com/5b174b64000128c702400240.jpg",
        "skill_color": "4a95dc"
      },
      {
        "id": "196",
        "name": "Spring入门篇",
        "short_description": "为您带来IOC和AOP的基本概念及用法，为后续高级课程学习打下基础",
        "pic": "//img2.mukewang.com/5704d2a90001bb1b06000338-590-330.jpg",
        "numbers": "248738",
        "type": 1,
        "share": "https://www.imooc.com/learn/196",
        "is_learned": 0,
        "learn_rate": -1,
        "is_pay": "0",
        "level": "中级",
        "skill_id": "220",
        "skill_name": "Java",
        "skill_pic": "//img2.mukewang.com/5b1746ca000157da02400240.jpg",
        "skill_color": "ff4545"
      },
      {
        "id": "317",
        "name": "python进阶",
        "short_description": "学习函数式、模块和面向对象编程，掌握Python高级程序设计",
        "pic": "//img2.mukewang.com/5705b7350001d59b06000338-590-330.jpg",
        "numbers": "243984",
        "type": 1,
        "share": "https://www.imooc.com/learn/317",
        "is_learned": 0,
        "learn_rate": -1,
        "is_pay": "0",
        "level": "中级",
        "skill_id": "1118",
        "skill_name": "Python",
        "skill_pic": "//img.mukewang.com/5b1746ed0001976102400240.jpg",
        "skill_color": "0070bb"
      },
      {
        "id": "166",
        "name": "JAVA遇见HTML——JSP篇",
        "short_description": "Java Web入门级教程JSP，带你轻松的学习JSP基础知识",
        "pic": "//img1.mukewang.com/576b7afb00019e4906000338-590-330.jpg",
        "numbers": "234039",
        "type": 1,
        "share": "https://www.imooc.com/learn/166",
        "is_learned": 0,
        "learn_rate": -1,
        "is_pay": "0",
        "level": "入门",
        "skill_id": "220",
        "skill_name": "Java",
        "skill_pic": "//img1.mukewang.com/5b1746ca000157da02400240.jpg",
        "skill_color": "ff4545"
      }
    ]
  }
}
